shore_kafka/__init__.py
shore_kafka/confs/__init__.py
shore_kafka/confs/examples.py
shore_kafka/consumers/__init__.py
shore_kafka/consumers/consumers.py
shore_kafka/producers/__init__.py
shore_kafka/producers/producers.py
shore_kafka/schema_registry/__init__.py
shore_kafka/schema_registry/builders.py
shore_kafka/schema_registry/schema_registry.py
shore_kafka-2022.1.6.dist-info/METADATA
shore_kafka-2022.1.6.dist-info/WHEEL
shore_kafka-2022.1.6.dist-info/entry_points.txt
shore_kafka-2022.1.6.dist-info/top_level.txt
shore_kafka-2022.1.6.dist-info/RECORD
